CHANGELOG.md
pymtheg.py
pymtheg-2.6.0.dist-info/entry_points.txt
pymtheg-2.6.0.dist-info/WHEEL
pymtheg-2.6.0.dist-info/METADATA
pymtheg-2.6.0.dist-info/RECORD
