Metadata-Version: 2.1
Name: pymtheg
Version: 2.6.0
Summary: A Python script to share songs from Spotify/YouTube as a 15 second clip.
Home-page: https://github.com/markjoshwel/pymtheg
Keywords: music,video,audio,cli,utility
Author: Your Name
Author-email: you@example.com
Requires-Python: >=3.6.3,<4.0.0
Classifier: Development Status :: 5 - Production/Stable
Classifier: Intended Audience :: End Users/Desktop
Classifier: License :: OSI Approved :: The Unlicense (Unlicense)
Classifier: License :: Public Domain
Classifier: Natural Language :: English
Classifier: Programming Language :: Python :: 3
Classifier: Programming Language :: Python :: 3.10
Classifier: Programming Language :: Python :: 3.7
Classifier: Programming Language :: Python :: 3.8
Classifier: Programming Language :: Python :: 3.9
Classifier: Topic :: Multimedia
Classifier: Topic :: Multimedia :: Sound/Audio
Classifier: Topic :: Multimedia :: Video
Classifier: Topic :: Utilities
Requires-Dist: rich (>=12.2.0,<13.0.0)
Requires-Dist: spotdl (>=3.9.4,<4.0.0)
Project-URL: Repository, https://github.com/markjoshwel/pymtheg
